unipy/__init__.py
unipy/fileinit.py
Pynity-0.0.1.dist-info/METADATA
Pynity-0.0.1.dist-info/WHEEL
Pynity-0.0.1.dist-info/top_level.txt
Pynity-0.0.1.dist-info/RECORD
