Metadata-Version: 2.1
Name: Pynity
Version: 0.0.1
Summary: Bring Unity coding into Python
Home-page: 
Author: Lime_Gradient
Author-email: limegradientyt@gmail.com
License: MIT
Platform: UNKNOWN
